[
  {
    "Export": {
      "Name": "CloneProgressStaticDataTable",
      "Class": "DataTable",
      "ClassOwner": "/Script/Engine",
      "Template": "Default__DataTable",
      "TemplateOwner": "/Script/Engine"
    },
    "Rows": {
    "FB01": {
      "CloneObjectivesID": [
        "FB01_2",
        "FB01_3",
        "FB01_4"
      ]
    },
    "FB_Team03_D": {
      "CloneObjectivesID": [
        "FB_Team03_D_2",
        "FB_Team03_D_3",
        "FB_Team03_D_5"
      ]
    },
    "FB_Team03_KN_D": {
      "CloneObjectivesID": [
        "FB_Team03_D_2",
        "FB_Team03_D_3",
        "FB_Team03_D_5"
      ]
    },
    "FB_Team03_SY_D": {
      "CloneObjectivesID": [
        "FB_Team03_D_2",
        "FB_Team03_D_3",
        "FB_Team03_D_5"
      ]
    },
    "FB_Team03_D_IV": {
      "CloneObjectivesID": [
        "FB_Team03_D_2",
        "FB_Team03_D_3",
        "FB_Team03_D_5"
      ]
    },
    "FB_Team03_D_V": {
      "CloneObjectivesID": [
        "FB_Team03_D_2",
        "FB_Team03_D_3",
        "FB_Team03_D_5"
      ]
    },
    "FB_Team03_D_VI": {
      "CloneObjectivesID": [
        "FB_Team03_D_2",
        "FB_Team03_D_3",
        "FB_Team03_D_5"
      ]
    },
    "FB_Team03_D_VII": {
      "CloneObjectivesID": [
        "FB_Team03_D_2",
        "FB_Team03_D_3",
        "FB_Team03_D_5"
      ]
    },
    "FB_Team03_D_VIII": {
      "CloneObjectivesID": [
        "FB_Team03_D_2",
        "FB_Team03_D_3",
        "FB_Team03_D_5"
      ]
    },
    "FB_Team02_D": {
      "CloneObjectivesID": [
        "FB_Team02_D_2",
        "FB_Team02_D_3",
        "FB_Team02_D_4",
        "FB_Team02_D_5",
        "FB_Team02_D_6",
        "FB_Team02_D_7",
        "FB_Team02_D_8",
        "FB_Team02_D_9",
        "FB_Team02_D_10"
      ]
    },
    "FB_Team02_KN_D": {
      "CloneObjectivesID": [
        "FB_Team02_D_2",
        "FB_Team02_D_3",
        "FB_Team02_D_4",
        "FB_Team02_D_5",
        "FB_Team02_D_6",
        "FB_Team02_D_7",
        "FB_Team02_D_8",
        "FB_Team02_D_9",
        "FB_Team02_D_10"
      ]
    },
    "FB_Team02_SY_D": {
      "CloneObjectivesID": [
        "FB_Team02_D_2",
        "FB_Team02_D_3",
        "FB_Team02_D_4",
        "FB_Team02_D_5",
        "FB_Team02_D_6",
        "FB_Team02_D_7",
        "FB_Team02_D_8",
        "FB_Team02_D_9",
        "FB_Team02_D_10"
      ]
    },
    "FB_Team02_D_IV": {
      "CloneObjectivesID": [
        "FB_Team02_D_2",
        "FB_Team02_D_3",
        "FB_Team02_D_4",
        "FB_Team02_D_5",
        "FB_Team02_D_6",
        "FB_Team02_D_7",
        "FB_Team02_D_8",
        "FB_Team02_D_9",
        "FB_Team02_D_10"
      ]
    },
    "FB_Team02_D_V": {
      "CloneObjectivesID": [
        "FB_Team02_D_2",
        "FB_Team02_D_3",
        "FB_Team02_D_4",
        "FB_Team02_D_5",
        "FB_Team02_D_6",
        "FB_Team02_D_7",
        "FB_Team02_D_8",
        "FB_Team02_D_9",
        "FB_Team02_D_10"
      ]
    },
    "FB_Team02_D_VI": {
      "CloneObjectivesID": [
        "FB_Team02_D_2",
        "FB_Team02_D_3",
        "FB_Team02_D_4",
        "FB_Team02_D_5",
        "FB_Team02_D_6",
        "FB_Team02_D_7",
        "FB_Team02_D_8",
        "FB_Team02_D_9",
        "FB_Team02_D_10"
      ]
    },
    "FB_Team02_D_VII": {
      "CloneObjectivesID": [
        "FB_Team02_D_2",
        "FB_Team02_D_3",
        "FB_Team02_D_4",
        "FB_Team02_D_5",
        "FB_Team02_D_6",
        "FB_Team02_D_7",
        "FB_Team02_D_8",
        "FB_Team02_D_9",
        "FB_Team02_D_10"
      ]
    },
    "FB_Team02_D_VIII": {
      "CloneObjectivesID": [
        "FB_Team02_D_2",
        "FB_Team02_D_3",
        "FB_Team02_D_4",
        "FB_Team02_D_5",
        "FB_Team02_D_6",
        "FB_Team02_D_7",
        "FB_Team02_D_8",
        "FB_Team02_D_9",
        "FB_Team02_D_10"
      ]
    },
    "FB_Team04_D": {
      "CloneObjectivesID": [
        "FB_Team04_D_2",
        "FB_Team04_D_3",
        "FB_Team04_D_4"
      ]
    },
    "FB_Team04_KN_D": {
      "CloneObjectivesID": [
        "FB_Team04_D_2",
        "FB_Team04_D_3",
        "FB_Team04_D_4"
      ]
    },
    "FB_Team04_SY_D": {
      "CloneObjectivesID": [
        "FB_Team04_D_2",
        "FB_Team04_D_3",
        "FB_Team04_D_4"
      ]
    },
    "FB_Team04_D_IV": {
      "CloneObjectivesID": [
        "FB_Team04_D_2",
        "FB_Team04_D_3",
        "FB_Team04_D_4"
      ]
    },
    "FB_Team04_D_V": {
      "CloneObjectivesID": [
        "FB_Team04_D_2",
        "FB_Team04_D_3",
        "FB_Team04_D_4"
      ]
    },
    "FB_Team04_D_VI": {
      "CloneObjectivesID": [
        "FB_Team04_D_2",
        "FB_Team04_D_3",
        "FB_Team04_D_4"
      ]
    },
    "FB_Team04_D_VII": {
      "CloneObjectivesID": [
        "FB_Team04_D_2",
        "FB_Team04_D_3",
        "FB_Team04_D_4"
      ]
    },
    "FB_Team04_D_VIII": {
      "CloneObjectivesID": [
        "FB_Team04_D_2",
        "FB_Team04_D_3",
        "FB_Team04_D_4"
      ]
    },
    "FB_Team05_D": {
      "CloneObjectivesID": [
        "FB_Team05_D_2",
        "FB_Team05_D_3",
        "FB_Team05_D_4"
      ]
    },
    "FB_Team05_KN_D": {
      "CloneObjectivesID": [
        "FB_Team05_D_2",
        "FB_Team05_D_3",
        "FB_Team05_D_4"
      ]
    },
    "FB_Team05_SY_D": {
      "CloneObjectivesID": [
        "FB_Team05_D_2",
        "FB_Team05_D_3",
        "FB_Team05_D_4"
      ]
    },
    "FB_Team05_D_IV": {
      "CloneObjectivesID": [
        "FB_Team05_D_2",
        "FB_Team05_D_3",
        "FB_Team05_D_4"
      ]
    },
    "FB_Team05_D_V": {
      "CloneObjectivesID": [
        "FB_Team05_D_2",
        "FB_Team05_D_3",
        "FB_Team05_D_4"
      ]
    },
    "FB_Team05_D_VI": {
      "CloneObjectivesID": [
        "FB_Team05_D_2",
        "FB_Team05_D_3",
        "FB_Team05_D_4"
      ]
    },
    "FB_Team05_D_VII": {
      "CloneObjectivesID": [
        "FB_Team05_D_2",
        "FB_Team05_D_3",
        "FB_Team05_D_4"
      ]
    },
    "FB_Team05_D_VIII": {
      "CloneObjectivesID": [
        "FB_Team05_D_2",
        "FB_Team05_D_3",
        "FB_Team05_D_4"
      ]
    },
    "FB_Team06_D": {
      "CloneObjectivesID": [
        "FB_Team06_D_2",
        "FB_Team06_D_3",
        "FB_Team06_D_4",
        "FB_Team06_D_5",
        "FB_Team06_D_6"
      ]
    },
    "FB_Team06_D_II": {
      "CloneObjectivesID": [
        "FB_Team06_D_2",
        "FB_Team06_D_3",
        "FB_Team06_D_4",
        "FB_Team06_D_5",
        "FB_Team06_D_6"
      ]
    },
    "FB_Team06_D_III": {
      "CloneObjectivesID": [
        "FB_Team06_D_2",
        "FB_Team06_D_3",
        "FB_Team06_D_4",
        "FB_Team06_D_5",
        "FB_Team06_D_6"
      ]
    },
    "FB_Team06_D_IV": {
      "CloneObjectivesID": [
        "FB_Team06_D_2",
        "FB_Team06_D_3",
        "FB_Team06_D_4",
        "FB_Team06_D_5",
        "FB_Team06_D_6"
      ]
    },
    "FB_Team06_D_V": {
      "CloneObjectivesID": [
        "FB_Team06_D_2",
        "FB_Team06_D_3",
        "FB_Team06_D_4",
        "FB_Team06_D_5",
        "FB_Team06_D_6"
      ]
    },
    "FB_Team06_D_VI": {
      "CloneObjectivesID": [
        "FB_Team06_D_2",
        "FB_Team06_D_3",
        "FB_Team06_D_4",
        "FB_Team06_D_5",
        "FB_Team06_D_6"
      ]
    },
    "FB_Team06_D_VII": {
      "CloneObjectivesID": [
        "FB_Team06_D_2",
        "FB_Team06_D_3",
        "FB_Team06_D_4",
        "FB_Team06_D_5",
        "FB_Team06_D_6"
      ]
    },
    "FB_Team06_D_VIII": {
      "CloneObjectivesID": [
        "FB_Team06_D_2",
        "FB_Team06_D_3",
        "FB_Team06_D_4",
        "FB_Team06_D_5",
        "FB_Team06_D_6"
      ]
    },
    "FB_Team07_D": {
      "CloneObjectivesID": [
        "FB_Team07_D_2",
        "FB_Team07_D_3",
        "FB_Team07_D_4",
        "FB_Team07_D_5"
      ]
    },
    "FB_Team07_D_II": {
      "CloneObjectivesID": [
        "FB_Team07_D_2",
        "FB_Team07_D_3",
        "FB_Team07_D_4",
        "FB_Team07_D_5"
      ]
    },
    "FB_Team07_D_III": {
      "CloneObjectivesID": [
        "FB_Team07_D_2",
        "FB_Team07_D_3",
        "FB_Team07_D_4",
        "FB_Team07_D_5"
      ]
    },
    "void001_D": {
      "CloneObjectivesID": [
        "void001",
        "void002"
      ]
    },
    "void002_D": {
      "CloneObjectivesID": [
        "void001",
        "void002"
      ]
    },
    "void003_D": {
      "CloneObjectivesID": [
        "void001",
        "void002"
      ]
    },
    "FB01_Random": {
      "CloneObjectivesID": [
        "FB01_Random"
      ]
    },
    "FB02_Random": {
      "CloneObjectivesID": [
        "FB02_Random"
      ]
    },
    "FB03_Random": {
      "CloneObjectivesID": [
        "FB03_Random"
      ]
    },
    "FB04_Random": {
      "CloneObjectivesID": [
        "FB04_Random"
      ]
    },
    "FB05_Random": {
      "CloneObjectivesID": [
        "FB05_Random"
      ]
    },
    "FB06_Random": {
      "CloneObjectivesID": [
        "FB06_Random"
      ]
    },
    "FB07_Random": {
      "CloneObjectivesID": [
        "FB07_Random"
      ]
    },
    "FB08_Random": {
      "CloneObjectivesID": [
        "FB08_Random"
      ]
    },
    "FB09_Random": {
      "CloneObjectivesID": [
        "FB09_Random"
      ]
    },
    "FB10_Random": {
      "CloneObjectivesID": [
        "FB10_Random"
      ]
    },
    "FB13_Random": {
      "CloneObjectivesID": [
        "FB13_Random"
      ]
    },
    "FB14_Random": {
      "CloneObjectivesID": [
        "FB14_Random"
      ]
    },
    "FB29_Random": {
      "CloneObjectivesID": [
        "FB29_Random"
      ]
    },
    "FB30_Random": {
      "CloneObjectivesID": [
        "FB30_Random"
      ]
    },
    "AstralPlane_L1_1_LD": {
      "CloneObjectivesID": [
        "AstralPlane"
      ]
    },
    "AstralPlane_L1_2_LD": {
      "CloneObjectivesID": [
        "AstralPlane"
      ]
    },
    "AstralPlane_L1_3_LD": {
      "CloneObjectivesID": [
        "AstralPlane"
      ]
    },
    "AstralPlane_L1_4_LD": {
      "CloneObjectivesID": [
        "AstralPlane"
      ]
    },
    "AstralPlane_L1_5_LD": {
      "CloneObjectivesID": [
        "AstralPlane"
      ]
    },
    "AstralPlane_L1_6_LD": {
      "CloneObjectivesID": [
        "AstralPlane"
      ]
    },
    "AstralPlane_L1_7_LD": {
      "CloneObjectivesID": [
        "AstralPlane"
      ]
    },
    "AstralPlane_L1_8_LD": {
      "CloneObjectivesID": [
        "AstralPlane"
      ]
    },
    "AstralPlane_L1_9_LD": {
      "CloneObjectivesID": [
        "AstralPlane"
      ]
    },
    "AstralPlane_L1_10_LD": {
      "CloneObjectivesID": [
        "AstralPlane"
      ]
    },
    "AstralPlane_L1_11_LD": {
      "CloneObjectivesID": [
        "AstralPlane"
      ]
    },
    "AstralPlane_L1_12_LD": {
      "CloneObjectivesID": [
        "AstralPlane"
      ]
    },
    "AstralPlane_L1_13_LD": {
      "CloneObjectivesID": [
        "AstralPlane"
      ]
    },
    "AstralPlane_L1_14_LD": {
      "CloneObjectivesID": [
        "AstralPlane"
      ]
    },
    "AstralPlane_L1_15_LD": {
      "CloneObjectivesID": [
        "AstralPlane"
      ]
    },
    "AstralPlane_L1_16_LD": {
      "CloneObjectivesID": [
        "AstralPlane"
      ]
    },
    "AstralPlane_L2_1_LD": {
      "CloneObjectivesID": [
        "AstralPlane"
      ]
    },
    "AstralPlane_L2_2_LD": {
      "CloneObjectivesID": [
        "AstralPlane"
      ]
    },
    "AstralPlane_L2_3_LD": {
      "CloneObjectivesID": [
        "AstralPlane"
      ]
    },
    "AstralPlane_L2_4_LD": {
      "CloneObjectivesID": [
        "AstralPlane"
      ]
    },
    "AstralPlane_L2_5_LD": {
      "CloneObjectivesID": [
        "AstralPlane"
      ]
    },
    "AstralPlane_L2_6_LD": {
      "CloneObjectivesID": [
        "AstralPlane"
      ]
    },
    "AstralPlane_L2_7_LD": {
      "CloneObjectivesID": [
        "AstralPlane"
      ]
    },
    "AstralPlane_L2_8_LD": {
      "CloneObjectivesID": [
        "AstralPlane"
      ]
    },
    "AstralPlane_L2_9_LD": {
      "CloneObjectivesID": [
        "AstralPlane"
      ]
    },
    "AstralPlane_L2_10_LD": {
      "CloneObjectivesID": [
        "AstralPlane"
      ]
    },
    "AstralPlane_L2_11_LD": {
      "CloneObjectivesID": [
        "AstralPlane"
      ]
    },
    "AstralPlane_L2_12_LD": {
      "CloneObjectivesID": [
        "AstralPlane"
      ]
    },
    "AstralPlane_L2_13_LD": {
      "CloneObjectivesID": [
        "AstralPlane"
      ]
    },
    "AstralPlane_L2_14_LD": {
      "CloneObjectivesID": [
        "AstralPlane"
      ]
    },
    "AstralPlane_L2_15_LD": {
      "CloneObjectivesID": [
        "AstralPlane"
      ]
    },
    "AstralPlane_L2_16_LD": {
      "CloneObjectivesID": [
        "AstralPlane"
      ]
    },
    "AstralPlane_L3_1_LD": {
      "CloneObjectivesID": [
        "AstralPlane"
      ]
    },
    "AstralPlane_L3_2_LD": {
      "CloneObjectivesID": [
        "AstralPlane"
      ]
    },
    "AstralPlane_L3_3_LD": {
      "CloneObjectivesID": [
        "AstralPlane"
      ]
    },
    "AstralPlane_L3_4_LD": {
      "CloneObjectivesID": [
        "AstralPlane"
      ]
    },
    "AstralPlane_L3_5_LD": {
      "CloneObjectivesID": [
        "AstralPlane"
      ]
    },
    "AstralPlane_L3_6_LD": {
      "CloneObjectivesID": [
        "AstralPlane"
      ]
    },
    "AstralPlane_L3_7_LD": {
      "CloneObjectivesID": [
        "AstralPlane"
      ]
    },
    "AstralPlane_L3_8_LD": {
      "CloneObjectivesID": [
        "AstralPlane"
      ]
    },
    "AstralPlane_L3_9_LD": {
      "CloneObjectivesID": [
        "AstralPlane"
      ]
    },
    "AstralPlane_L3_10_LD": {
      "CloneObjectivesID": [
        "AstralPlane"
      ]
    },
    "AstralPlane_L3_11_LD": {
      "CloneObjectivesID": [
        "AstralPlane"
      ]
    },
    "AstralPlane_L3_12_LD": {
      "CloneObjectivesID": [
        "AstralPlane"
      ]
    },
    "AstralPlane_L3_13_LD": {
      "CloneObjectivesID": [
        "AstralPlane"
      ]
    },
    "AstralPlane_L3_14_LD": {
      "CloneObjectivesID": [
        "AstralPlane"
      ]
    },
    "AstralPlane_L3_15_LD": {
      "CloneObjectivesID": [
        "AstralPlane"
      ]
    },
    "AstralPlane_L3_16_LD": {
      "CloneObjectivesID": [
        "AstralPlane"
      ]
    },
    "AstralPlane_Red_L3_1_LD": {
      "CloneObjectivesID": [
        "AstralPlane_Red"
      ]
    },
    "AstralPlane_Red_L3_2_LD": {
      "CloneObjectivesID": [
        "AstralPlane_Red"
      ]
    },
    "AstralPlane_Red_L3_5_LD": {
      "CloneObjectivesID": [
        "AstralPlane_Red"
      ]
    },
    "AstralPlane_Red_L3_6_LD": {
      "CloneObjectivesID": [
        "AstralPlane_Red"
      ]
    },
    "AstralPlane_Red_L3_7_LD": {
      "CloneObjectivesID": [
        "AstralPlane_Red"
      ]
    },
    "AstralPlane_Red_L3_8_LD": {
      "CloneObjectivesID": [
        "AstralPlane_Red"
      ]
    },
    "AstralPlane_SP_Charger_1_LD": {
      "CloneObjectivesID": [
        "AstralPlane_Charger_SpecialAP"
      ]
    },
    "AstralPlane_SP_Charger_2_LD": {
      "CloneObjectivesID": [
        "AstralPlane_Charger_SpecialAP"
      ]
    },
    "AstralPlane_SP_PW_1_LD": {
      "CloneObjectivesID": [
        "AstralPlane_PW_SpecialAP"
      ]
    },
    "AstralPlane_SP_PW_2_LD": {
      "CloneObjectivesID": [
        "AstralPlane_PW_SpecialAP"
      ]
    },
    "AstralPlane_SP_PW_3_LD": {
      "CloneObjectivesID": [
        "AstralPlane_PW_SpecialAP"
      ]
    },
    "AstralPlane_SP_Boss_1_LD": {
      "CloneObjectivesID": [
        "AstralPlane_Red"
      ]
    },
    "AstralPlane_SP_Boss_2_LD": {
      "CloneObjectivesID": [
        "AstralPlane_Red"
      ]
    },
    "AstralPlane_SP_Boss_3_LD": {
      "CloneObjectivesID": [
        "AstralPlane_Red"
      ]
    },
    "FB25_Random": {
      "CloneObjectivesID": [
        "FB25_Random"
      ]
    },
    "FB_Intruder": {
      "CloneObjectivesID": [
        "FB_Intruder"
      ]
    },
    "FB_Intruder_Hard": {
      "CloneObjectivesID": [
        "FB_Intruder"
      ]
    },
    "FB_Executor_Normal": {
      "CloneObjectivesID": [
        "FB_Executor"
      ]
    },
    "FB_Executor_Hard": {
      "CloneObjectivesID": [
        "FB_Executor"
      ]
    },
    "Team8P_01_D": {
      "CloneObjectivesID": [
        "Team8P_01_D_2"
      ]
    },
    "Team8P_01_D_II": {
      "CloneObjectivesID": [
        "Team8P_01_D_2"
      ]
    },
    "Team8P_02_D": {
      "CloneObjectivesID": [
        "Team8P_02_D_2"
      ]
    },
    "Team8P_02_D_II": {
      "CloneObjectivesID": [
        "Team8P_02_D_2"
      ]
    },
    "Team8P_03_D": {
      "CloneObjectivesID": [
        "Team8P_03_D_2"
      ]
    },
    "Team8P_03_D_II": {
      "CloneObjectivesID": [
        "Team8P_03_D_2"
      ]
    },
    "team_active_01_D": {
      "CloneObjectivesID": [
        "team_active_01_D"
      ]
    },
    "team_active_01_KN_D": {
      "CloneObjectivesID": [
        "team_active_01_D"
      ]
    }
  }
  }
]