[
  {
    "Export": {
      "Name": "DT_ClientGroupConfig_Vera",
      "Class": "DataTable",
      "ClassOwner": "/Script/Engine",
      "Template": "Default__DataTable",
      "TemplateOwner": "/Script/Engine"
    },
    "Rows": {
    "Vera_Taxi_A2": {
      "GroupId": -1,
      "GroupLevelId": "None",
      "LeaveDelayTime": 0,
      "Level": {
        "Path": "/Game/Resources/CoreBlueprints/Trial/Vera_city/Taxi/Vera_Taxi_A2.Vera_Taxi_A2",
        "SubPath": ""
      },
      "EntryParticle": {
        "Path": "None",
        "SubPath": ""
      },
      "LeaveParticle": {
        "Path": "None",
        "SubPath": ""
      },
      "bDisableOther": true,
      "ChangGround": true,
      "ShowEntryNotifyInfo": false,
      "ShowLeaveNotifyInfo": false,
      "IsQuestGroup": false,
      "KeepSkateboardState": false,
      "KeepAllState": false,
      "QuestList": []
    },
    "Vera_Taxi_A3": {
      "GroupId": -1,
      "GroupLevelId": "None",
      "LeaveDelayTime": 0,
      "Level": {
        "Path": "/Game/Resources/CoreBlueprints/Trial/Vera_city/Taxi/Vera_Taxi_A3.Vera_Taxi_A3",
        "SubPath": ""
      },
      "EntryParticle": {
        "Path": "None",
        "SubPath": ""
      },
      "LeaveParticle": {
        "Path": "None",
        "SubPath": ""
      },
      "bDisableOther": true,
      "ChangGround": true,
      "ShowEntryNotifyInfo": false,
      "ShowLeaveNotifyInfo": false,
      "IsQuestGroup": false,
      "KeepSkateboardState": false,
      "KeepAllState": false,
      "QuestList": []
    },
    "v101056": {
      "GroupId": -1,
      "GroupLevelId": "None",
      "LeaveDelayTime": 1,
      "Level": {
        "Path": "/Game/Resources/DynamicLevels/Vera/Vera_Quest_wzy/v101056.v101056",
        "SubPath": ""
      },
      "EntryParticle": {
        "Path": "None",
        "SubPath": ""
      },
      "LeaveParticle": {
        "Path": "None",
        "SubPath": ""
      },
      "bDisableOther": true,
      "ChangGround": true,
      "ShowEntryNotifyInfo": false,
      "ShowLeaveNotifyInfo": false,
      "IsQuestGroup": true,
      "KeepSkateboardState": false,
      "KeepAllState": false,
      "QuestList": []
    },
    "v101057": {
      "GroupId": -1,
      "GroupLevelId": "None",
      "LeaveDelayTime": 1,
      "Level": {
        "Path": "/Game/Resources/DynamicLevels/Vera/Vera_Quest_wzy/v101057.v101057",
        "SubPath": ""
      },
      "EntryParticle": {
        "Path": "None",
        "SubPath": ""
      },
      "LeaveParticle": {
        "Path": "None",
        "SubPath": ""
      },
      "bDisableOther": true,
      "ChangGround": true,
      "ShowEntryNotifyInfo": false,
      "ShowLeaveNotifyInfo": false,
      "IsQuestGroup": true,
      "KeepSkateboardState": false,
      "KeepAllState": false,
      "QuestList": []
    },
    "v101058": {
      "GroupId": -1,
      "GroupLevelId": "None",
      "LeaveDelayTime": 1,
      "Level": {
        "Path": "/Game/Resources/DynamicLevels/Vera/Vera_Quest_wzy/v101058.v101058",
        "SubPath": ""
      },
      "EntryParticle": {
        "Path": "None",
        "SubPath": ""
      },
      "LeaveParticle": {
        "Path": "None",
        "SubPath": ""
      },
      "bDisableOther": true,
      "ChangGround": true,
      "ShowEntryNotifyInfo": false,
      "ShowLeaveNotifyInfo": false,
      "IsQuestGroup": true,
      "KeepSkateboardState": false,
      "KeepAllState": false,
      "QuestList": []
    },
    "v101059": {
      "GroupId": -1,
      "GroupLevelId": "None",
      "LeaveDelayTime": 1,
      "Level": {
        "Path": "/Game/Resources/DynamicLevels/Vera/Vera_Quest_wzy/v101059.v101059",
        "SubPath": ""
      },
      "EntryParticle": {
        "Path": "None",
        "SubPath": ""
      },
      "LeaveParticle": {
        "Path": "None",
        "SubPath": ""
      },
      "bDisableOther": true,
      "ChangGround": true,
      "ShowEntryNotifyInfo": false,
      "ShowLeaveNotifyInfo": false,
      "IsQuestGroup": true,
      "KeepSkateboardState": false,
      "KeepAllState": false,
      "QuestList": []
    },
    "v1010591": {
      "GroupId": -1,
      "GroupLevelId": "None",
      "LeaveDelayTime": 1,
      "Level": {
        "Path": "/Game/Resources/DynamicLevels/Vera/Vera_Quest_wzy/v101059.v101059",
        "SubPath": ""
      },
      "EntryParticle": {
        "Path": "None",
        "SubPath": ""
      },
      "LeaveParticle": {
        "Path": "None",
        "SubPath": ""
      },
      "bDisableOther": true,
      "ChangGround": true,
      "ShowEntryNotifyInfo": false,
      "ShowLeaveNotifyInfo": false,
      "IsQuestGroup": true,
      "KeepSkateboardState": false,
      "KeepAllState": false,
      "QuestList": []
    },
    "v101072": {
      "GroupId": -1,
      "GroupLevelId": "None",
      "LeaveDelayTime": 3,
      "Level": {
        "Path": "/Game/Resources/DynamicLevels/Vera/Vera_Quest_sly/v101072.v101072",
        "SubPath": ""
      },
      "EntryParticle": {
        "Path": "/Game/Resources/Abilities/GameCue/Effect/Effect_ClientGroup.Effect_ClientGroup_C",
        "SubPath": ""
      },
      "LeaveParticle": {
        "Path": "None",
        "SubPath": ""
      },
      "bDisableOther": true,
      "ChangGround": false,
      "ShowEntryNotifyInfo": true,
      "ShowLeaveNotifyInfo": false,
      "IsQuestGroup": true,
      "KeepSkateboardState": false,
      "KeepAllState": false,
      "QuestList": []
    },
    "v101073": {
      "GroupId": -1,
      "GroupLevelId": "None",
      "LeaveDelayTime": 2,
      "Level": {
        "Path": "/Game/Resources/DynamicLevels/Vera/Vera_Quest_sly/v101072.v101072",
        "SubPath": ""
      },
      "EntryParticle": {
        "Path": "None",
        "SubPath": ""
      },
      "LeaveParticle": {
        "Path": "None",
        "SubPath": ""
      },
      "bDisableOther": true,
      "ChangGround": true,
      "ShowEntryNotifyInfo": false,
      "ShowLeaveNotifyInfo": false,
      "IsQuestGroup": true,
      "KeepSkateboardState": false,
      "KeepAllState": false,
      "QuestList": []
    },
    "v101075": {
      "GroupId": -1,
      "GroupLevelId": "None",
      "LeaveDelayTime": 3,
      "Level": {
        "Path": "/Game/Resources/DynamicLevels/Vera/Vera_Quest_sly/v101075.v101075",
        "SubPath": ""
      },
      "EntryParticle": {
        "Path": "None",
        "SubPath": ""
      },
      "LeaveParticle": {
        "Path": "None",
        "SubPath": ""
      },
      "bDisableOther": true,
      "ChangGround": false,
      "ShowEntryNotifyInfo": true,
      "ShowLeaveNotifyInfo": false,
      "IsQuestGroup": true,
      "KeepSkateboardState": false,
      "KeepAllState": false,
      "QuestList": []
    },
    "v101076": {
      "GroupId": -1,
      "GroupLevelId": "None",
      "LeaveDelayTime": 3,
      "Level": {
        "Path": "/Game/Resources/DynamicLevels/Vera/Vera_Quest_sly/v101075.v101075",
        "SubPath": ""
      },
      "EntryParticle": {
        "Path": "None",
        "SubPath": ""
      },
      "LeaveParticle": {
        "Path": "None",
        "SubPath": ""
      },
      "bDisableOther": true,
      "ChangGround": false,
      "ShowEntryNotifyInfo": false,
      "ShowLeaveNotifyInfo": false,
      "IsQuestGroup": true,
      "KeepSkateboardState": false,
      "KeepAllState": false,
      "QuestList": []
    },
    "v101077": {
      "GroupId": -1,
      "GroupLevelId": "None",
      "LeaveDelayTime": 3,
      "Level": {
        "Path": "/Game/Resources/DynamicLevels/Vera/Vera_Quest_sly/v101075.v101075",
        "SubPath": ""
      },
      "EntryParticle": {
        "Path": "None",
        "SubPath": ""
      },
      "LeaveParticle": {
        "Path": "None",
        "SubPath": ""
      },
      "bDisableOther": true,
      "ChangGround": false,
      "ShowEntryNotifyInfo": false,
      "ShowLeaveNotifyInfo": false,
      "IsQuestGroup": true,
      "KeepSkateboardState": false,
      "KeepAllState": false,
      "QuestList": []
    },
    "v101078": {
      "GroupId": -1,
      "GroupLevelId": "None",
      "LeaveDelayTime": 0,
      "Level": {
        "Path": "/Game/Resources/DynamicLevels/Vera/Vera_Quest_sly/v101075.v101075",
        "SubPath": ""
      },
      "EntryParticle": {
        "Path": "None",
        "SubPath": ""
      },
      "LeaveParticle": {
        "Path": "None",
        "SubPath": ""
      },
      "bDisableOther": false,
      "ChangGround": false,
      "ShowEntryNotifyInfo": false,
      "ShowLeaveNotifyInfo": false,
      "IsQuestGroup": true,
      "KeepSkateboardState": false,
      "KeepAllState": false,
      "QuestList": []
    },
    "v101007": {
      "GroupId": -1,
      "GroupLevelId": "None",
      "LeaveDelayTime": 1,
      "Level": {
        "Path": "/Game/Resources/DynamicLevels/Vera/Vera_Quest_pgl/v101007.v101007",
        "SubPath": ""
      },
      "EntryParticle": {
        "Path": "None",
        "SubPath": ""
      },
      "LeaveParticle": {
        "Path": "None",
        "SubPath": ""
      },
      "bDisableOther": false,
      "ChangGround": true,
      "ShowEntryNotifyInfo": false,
      "ShowLeaveNotifyInfo": false,
      "IsQuestGroup": true,
      "KeepSkateboardState": false,
      "KeepAllState": false,
      "QuestList": []
    },
    "v101008": {
      "GroupId": -1,
      "GroupLevelId": "None",
      "LeaveDelayTime": 1,
      "Level": {
        "Path": "/Game/Resources/DynamicLevels/Vera/Vera_Quest_pgl/v101007.v101007",
        "SubPath": ""
      },
      "EntryParticle": {
        "Path": "None",
        "SubPath": ""
      },
      "LeaveParticle": {
        "Path": "None",
        "SubPath": ""
      },
      "bDisableOther": false,
      "ChangGround": true,
      "ShowEntryNotifyInfo": false,
      "ShowLeaveNotifyInfo": false,
      "IsQuestGroup": true,
      "KeepSkateboardState": false,
      "KeepAllState": false,
      "QuestList": []
    },
    "v101009": {
      "GroupId": -1,
      "GroupLevelId": "None",
      "LeaveDelayTime": 1,
      "Level": {
        "Path": "/Game/Resources/DynamicLevels/Vera/Vera_Quest_pgl/v101007.v101007",
        "SubPath": ""
      },
      "EntryParticle": {
        "Path": "None",
        "SubPath": ""
      },
      "LeaveParticle": {
        "Path": "None",
        "SubPath": ""
      },
      "bDisableOther": false,
      "ChangGround": true,
      "ShowEntryNotifyInfo": false,
      "ShowLeaveNotifyInfo": false,
      "IsQuestGroup": true,
      "KeepSkateboardState": false,
      "KeepAllState": false,
      "QuestList": []
    },
    "v101010": {
      "GroupId": -1,
      "GroupLevelId": "None",
      "LeaveDelayTime": 1.5,
      "Level": {
        "Path": "/Game/Resources/DynamicLevels/Vera/Vera_Quest_pgl/v101010.v101010",
        "SubPath": ""
      },
      "EntryParticle": {
        "Path": "None",
        "SubPath": ""
      },
      "LeaveParticle": {
        "Path": "None",
        "SubPath": ""
      },
      "bDisableOther": false,
      "ChangGround": true,
      "ShowEntryNotifyInfo": false,
      "ShowLeaveNotifyInfo": false,
      "IsQuestGroup": true,
      "KeepSkateboardState": false,
      "KeepAllState": false,
      "QuestList": []
    },
    "v101012": {
      "GroupId": -1,
      "GroupLevelId": "None",
      "LeaveDelayTime": 1,
      "Level": {
        "Path": "/Game/Resources/DynamicLevels/Vera/Vera_Quest_pgl/v101012.v101012",
        "SubPath": ""
      },
      "EntryParticle": {
        "Path": "None",
        "SubPath": ""
      },
      "LeaveParticle": {
        "Path": "None",
        "SubPath": ""
      },
      "bDisableOther": false,
      "ChangGround": true,
      "ShowEntryNotifyInfo": false,
      "ShowLeaveNotifyInfo": false,
      "IsQuestGroup": true,
      "KeepSkateboardState": false,
      "KeepAllState": false,
      "QuestList": []
    },
    "v1010131": {
      "GroupId": -1,
      "GroupLevelId": "None",
      "LeaveDelayTime": 1,
      "Level": {
        "Path": "/Game/Resources/DynamicLevels/Vera/Vera_Quest_pgl/v1010131.v1010131",
        "SubPath": ""
      },
      "EntryParticle": {
        "Path": "None",
        "SubPath": ""
      },
      "LeaveParticle": {
        "Path": "/Game/Resources/Abilities/GameCue/Effect/Effect_ClientGroup.Effect_ClientGroup_C",
        "SubPath": ""
      },
      "bDisableOther": false,
      "ChangGround": true,
      "ShowEntryNotifyInfo": false,
      "ShowLeaveNotifyInfo": true,
      "IsQuestGroup": true,
      "KeepSkateboardState": false,
      "KeepAllState": false,
      "QuestList": []
    },
    "v101080": {
      "GroupId": -1,
      "GroupLevelId": "None",
      "LeaveDelayTime": 3,
      "Level": {
        "Path": "/Game/Resources/DynamicLevels/Vera/Vera_Quest_sly/v101080.v101080",
        "SubPath": ""
      },
      "EntryParticle": {
        "Path": "None",
        "SubPath": ""
      },
      "LeaveParticle": {
        "Path": "None",
        "SubPath": ""
      },
      "bDisableOther": true,
      "ChangGround": false,
      "ShowEntryNotifyInfo": false,
      "ShowLeaveNotifyInfo": false,
      "IsQuestGroup": true,
      "KeepSkateboardState": false,
      "KeepAllState": false,
      "QuestList": []
    },
    "v101081": {
      "GroupId": -1,
      "GroupLevelId": "None",
      "LeaveDelayTime": 3,
      "Level": {
        "Path": "/Game/Resources/DynamicLevels/Vera/Vera_Quest_sly/v101080.v101080",
        "SubPath": ""
      },
      "EntryParticle": {
        "Path": "None",
        "SubPath": ""
      },
      "LeaveParticle": {
        "Path": "None",
        "SubPath": ""
      },
      "bDisableOther": true,
      "ChangGround": false,
      "ShowEntryNotifyInfo": false,
      "ShowLeaveNotifyInfo": false,
      "IsQuestGroup": true,
      "KeepSkateboardState": false,
      "KeepAllState": false,
      "QuestList": []
    },
    "v101082": {
      "GroupId": -1,
      "GroupLevelId": "None",
      "LeaveDelayTime": 3,
      "Level": {
        "Path": "/Game/Resources/DynamicLevels/Vera/Vera_Quest_sly/v101080.v101080",
        "SubPath": ""
      },
      "EntryParticle": {
        "Path": "None",
        "SubPath": ""
      },
      "LeaveParticle": {
        "Path": "None",
        "SubPath": ""
      },
      "bDisableOther": true,
      "ChangGround": false,
      "ShowEntryNotifyInfo": false,
      "ShowLeaveNotifyInfo": false,
      "IsQuestGroup": true,
      "KeepSkateboardState": false,
      "KeepAllState": false,
      "QuestList": []
    },
    "v101083": {
      "GroupId": -1,
      "GroupLevelId": "None",
      "LeaveDelayTime": 3,
      "Level": {
        "Path": "/Game/Resources/DynamicLevels/Vera/Vera_Quest_sly/v101080.v101080",
        "SubPath": ""
      },
      "EntryParticle": {
        "Path": "None",
        "SubPath": ""
      },
      "LeaveParticle": {
        "Path": "None",
        "SubPath": ""
      },
      "bDisableOther": true,
      "ChangGround": false,
      "ShowEntryNotifyInfo": false,
      "ShowLeaveNotifyInfo": false,
      "IsQuestGroup": true,
      "KeepSkateboardState": false,
      "KeepAllState": false,
      "QuestList": []
    },
    "v101084": {
      "GroupId": -1,
      "GroupLevelId": "None",
      "LeaveDelayTime": 3,
      "Level": {
        "Path": "/Game/Resources/DynamicLevels/Vera/Vera_Quest_sly/v101080.v101080",
        "SubPath": ""
      },
      "EntryParticle": {
        "Path": "None",
        "SubPath": ""
      },
      "LeaveParticle": {
        "Path": "None",
        "SubPath": ""
      },
      "bDisableOther": true,
      "ChangGround": false,
      "ShowEntryNotifyInfo": false,
      "ShowLeaveNotifyInfo": false,
      "IsQuestGroup": true,
      "KeepSkateboardState": false,
      "KeepAllState": false,
      "QuestList": []
    },
    "v101085": {
      "GroupId": -1,
      "GroupLevelId": "None",
      "LeaveDelayTime": 3,
      "Level": {
        "Path": "/Game/Resources/DynamicLevels/Vera/Vera_Quest_sly/v101080.v101080",
        "SubPath": ""
      },
      "EntryParticle": {
        "Path": "None",
        "SubPath": ""
      },
      "LeaveParticle": {
        "Path": "None",
        "SubPath": ""
      },
      "bDisableOther": true,
      "ChangGround": false,
      "ShowEntryNotifyInfo": false,
      "ShowLeaveNotifyInfo": false,
      "IsQuestGroup": true,
      "KeepSkateboardState": false,
      "KeepAllState": false,
      "QuestList": []
    },
    "v101086": {
      "GroupId": -1,
      "GroupLevelId": "None",
      "LeaveDelayTime": 3,
      "Level": {
        "Path": "/Game/Resources/DynamicLevels/Vera/Vera_Quest_sly/v101080.v101080",
        "SubPath": ""
      },
      "EntryParticle": {
        "Path": "None",
        "SubPath": ""
      },
      "LeaveParticle": {
        "Path": "None",
        "SubPath": ""
      },
      "bDisableOther": true,
      "ChangGround": false,
      "ShowEntryNotifyInfo": false,
      "ShowLeaveNotifyInfo": false,
      "IsQuestGroup": true,
      "KeepSkateboardState": false,
      "KeepAllState": false,
      "QuestList": []
    },
    "v101087": {
      "GroupId": -1,
      "GroupLevelId": "None",
      "LeaveDelayTime": 3,
      "Level": {
        "Path": "/Game/Resources/DynamicLevels/Vera/Vera_Quest_sly/v101080.v101080",
        "SubPath": ""
      },
      "EntryParticle": {
        "Path": "None",
        "SubPath": ""
      },
      "LeaveParticle": {
        "Path": "None",
        "SubPath": ""
      },
      "bDisableOther": true,
      "ChangGround": false,
      "ShowEntryNotifyInfo": false,
      "ShowLeaveNotifyInfo": false,
      "IsQuestGroup": true,
      "KeepSkateboardState": false,
      "KeepAllState": false,
      "QuestList": []
    },
    "v101088": {
      "GroupId": -1,
      "GroupLevelId": "None",
      "LeaveDelayTime": 3,
      "Level": {
        "Path": "/Game/Resources/DynamicLevels/Vera/Vera_Quest_sly/v101080.v101080",
        "SubPath": ""
      },
      "EntryParticle": {
        "Path": "None",
        "SubPath": ""
      },
      "LeaveParticle": {
        "Path": "None",
        "SubPath": ""
      },
      "bDisableOther": true,
      "ChangGround": false,
      "ShowEntryNotifyInfo": false,
      "ShowLeaveNotifyInfo": false,
      "IsQuestGroup": true,
      "KeepSkateboardState": false,
      "KeepAllState": false,
      "QuestList": []
    },
    "v101089": {
      "GroupId": -1,
      "GroupLevelId": "None",
      "LeaveDelayTime": 3,
      "Level": {
        "Path": "/Game/Resources/DynamicLevels/Vera/Vera_Quest_sly/v101080.v101080",
        "SubPath": ""
      },
      "EntryParticle": {
        "Path": "None",
        "SubPath": ""
      },
      "LeaveParticle": {
        "Path": "None",
        "SubPath": ""
      },
      "bDisableOther": true,
      "ChangGround": false,
      "ShowEntryNotifyInfo": false,
      "ShowLeaveNotifyInfo": false,
      "IsQuestGroup": true,
      "KeepSkateboardState": false,
      "KeepAllState": false,
      "QuestList": []
    },
    "v101090": {
      "GroupId": -1,
      "GroupLevelId": "None",
      "LeaveDelayTime": 3,
      "Level": {
        "Path": "/Game/Resources/DynamicLevels/Vera/Vera_Quest_sly/v101080.v101080",
        "SubPath": ""
      },
      "EntryParticle": {
        "Path": "None",
        "SubPath": ""
      },
      "LeaveParticle": {
        "Path": "None",
        "SubPath": ""
      },
      "bDisableOther": true,
      "ChangGround": false,
      "ShowEntryNotifyInfo": false,
      "ShowLeaveNotifyInfo": true,
      "IsQuestGroup": true,
      "KeepSkateboardState": false,
      "KeepAllState": false,
      "QuestList": []
    },
    "v101094": {
      "GroupId": -1,
      "GroupLevelId": "None",
      "LeaveDelayTime": 3,
      "Level": {
        "Path": "/Game/Resources/DynamicLevels/Vera/Vera_Quest_sly/v101094.v101094",
        "SubPath": ""
      },
      "EntryParticle": {
        "Path": "None",
        "SubPath": ""
      },
      "LeaveParticle": {
        "Path": "None",
        "SubPath": ""
      },
      "bDisableOther": true,
      "ChangGround": false,
      "ShowEntryNotifyInfo": false,
      "ShowLeaveNotifyInfo": false,
      "IsQuestGroup": true,
      "KeepSkateboardState": false,
      "KeepAllState": false,
      "QuestList": []
    },
    "v101095": {
      "GroupId": -1,
      "GroupLevelId": "None",
      "LeaveDelayTime": 3,
      "Level": {
        "Path": "/Game/Resources/DynamicLevels/Vera/Vera_Quest_sly/v101094.v101094",
        "SubPath": ""
      },
      "EntryParticle": {
        "Path": "None",
        "SubPath": ""
      },
      "LeaveParticle": {
        "Path": "None",
        "SubPath": ""
      },
      "bDisableOther": true,
      "ChangGround": false,
      "ShowEntryNotifyInfo": false,
      "ShowLeaveNotifyInfo": false,
      "IsQuestGroup": true,
      "KeepSkateboardState": false,
      "KeepAllState": false,
      "QuestList": []
    },
    "v101096": {
      "GroupId": -1,
      "GroupLevelId": "None",
      "LeaveDelayTime": 3,
      "Level": {
        "Path": "/Game/Resources/DynamicLevels/Vera/Vera_Quest_sly/v101094.v101094",
        "SubPath": ""
      },
      "EntryParticle": {
        "Path": "None",
        "SubPath": ""
      },
      "LeaveParticle": {
        "Path": "None",
        "SubPath": ""
      },
      "bDisableOther": true,
      "ChangGround": false,
      "ShowEntryNotifyInfo": false,
      "ShowLeaveNotifyInfo": false,
      "IsQuestGroup": true,
      "KeepSkateboardState": false,
      "KeepAllState": false,
      "QuestList": []
    },
    "v101097": {
      "GroupId": -1,
      "GroupLevelId": "None",
      "LeaveDelayTime": 3,
      "Level": {
        "Path": "/Game/Resources/DynamicLevels/Vera/Vera_Quest_sly/v101094.v101094",
        "SubPath": ""
      },
      "EntryParticle": {
        "Path": "None",
        "SubPath": ""
      },
      "LeaveParticle": {
        "Path": "None",
        "SubPath": ""
      },
      "bDisableOther": true,
      "ChangGround": false,
      "ShowEntryNotifyInfo": false,
      "ShowLeaveNotifyInfo": false,
      "IsQuestGroup": true,
      "KeepSkateboardState": false,
      "KeepAllState": false,
      "QuestList": []
    },
    "v101101": {
      "GroupId": -1,
      "GroupLevelId": "None",
      "LeaveDelayTime": 3,
      "Level": {
        "Path": "/Game/Resources/DynamicLevels/Vera/Vera_Quest_sly/v101100.v101100",
        "SubPath": ""
      },
      "EntryParticle": {
        "Path": "None",
        "SubPath": ""
      },
      "LeaveParticle": {
        "Path": "None",
        "SubPath": ""
      },
      "bDisableOther": false,
      "ChangGround": false,
      "ShowEntryNotifyInfo": false,
      "ShowLeaveNotifyInfo": true,
      "IsQuestGroup": true,
      "KeepSkateboardState": false,
      "KeepAllState": false,
      "QuestList": []
    },
    "v101102": {
      "GroupId": -1,
      "GroupLevelId": "None",
      "LeaveDelayTime": 3,
      "Level": {
        "Path": "/Game/Resources/DynamicLevels/Vera/Vera_Quest_sly/v101100.v101100",
        "SubPath": ""
      },
      "EntryParticle": {
        "Path": "None",
        "SubPath": ""
      },
      "LeaveParticle": {
        "Path": "None",
        "SubPath": ""
      },
      "bDisableOther": false,
      "ChangGround": false,
      "ShowEntryNotifyInfo": false,
      "ShowLeaveNotifyInfo": true,
      "IsQuestGroup": true,
      "KeepSkateboardState": false,
      "KeepAllState": false,
      "QuestList": []
    },
    "v101109": {
      "GroupId": -1,
      "GroupLevelId": "None",
      "LeaveDelayTime": 3,
      "Level": {
        "Path": "/Game/Resources/DynamicLevels/Vera/Vera_Quest_sly/v101100.v101100",
        "SubPath": ""
      },
      "EntryParticle": {
        "Path": "None",
        "SubPath": ""
      },
      "LeaveParticle": {
        "Path": "None",
        "SubPath": ""
      },
      "bDisableOther": false,
      "ChangGround": false,
      "ShowEntryNotifyInfo": false,
      "ShowLeaveNotifyInfo": false,
      "IsQuestGroup": true,
      "KeepSkateboardState": false,
      "KeepAllState": false,
      "QuestList": []
    },
    "v1011091": {
      "GroupId": -1,
      "GroupLevelId": "None",
      "LeaveDelayTime": 0,
      "Level": {
        "Path": "/Game/Resources/DynamicLevels/Vera/Vera_Quest_sly/v101100.v101100",
        "SubPath": ""
      },
      "EntryParticle": {
        "Path": "None",
        "SubPath": ""
      },
      "LeaveParticle": {
        "Path": "None",
        "SubPath": ""
      },
      "bDisableOther": false,
      "ChangGround": false,
      "ShowEntryNotifyInfo": false,
      "ShowLeaveNotifyInfo": true,
      "IsQuestGroup": true,
      "KeepSkateboardState": false,
      "KeepAllState": false,
      "QuestList": []
    },
    "v602003": {
      "GroupId": -1,
      "GroupLevelId": "None",
      "LeaveDelayTime": 3,
      "Level": {
        "Path": "/Game/Resources/CoreBlueprints/SceneItem/vera_zdy/sidequest/v602002.v602002",
        "SubPath": ""
      },
      "EntryParticle": {
        "Path": "None",
        "SubPath": ""
      },
      "LeaveParticle": {
        "Path": "None",
        "SubPath": ""
      },
      "bDisableOther": true,
      "ChangGround": false,
      "ShowEntryNotifyInfo": false,
      "ShowLeaveNotifyInfo": false,
      "IsQuestGroup": true,
      "KeepSkateboardState": false,
      "KeepAllState": false,
      "QuestList": []
    },
    "v602004": {
      "GroupId": -1,
      "GroupLevelId": "None",
      "LeaveDelayTime": 3,
      "Level": {
        "Path": "/Game/Resources/CoreBlueprints/SceneItem/vera_zdy/sidequest/v602002.v602002",
        "SubPath": ""
      },
      "EntryParticle": {
        "Path": "None",
        "SubPath": ""
      },
      "LeaveParticle": {
        "Path": "None",
        "SubPath": ""
      },
      "bDisableOther": true,
      "ChangGround": false,
      "ShowEntryNotifyInfo": false,
      "ShowLeaveNotifyInfo": false,
      "IsQuestGroup": true,
      "KeepSkateboardState": false,
      "KeepAllState": false,
      "QuestList": []
    },
    "v602006": {
      "GroupId": -1,
      "GroupLevelId": "None",
      "LeaveDelayTime": 3,
      "Level": {
        "Path": "/Game/Resources/CoreBlueprints/SceneItem/vera_zdy/sidequest/v602005.v602005",
        "SubPath": ""
      },
      "EntryParticle": {
        "Path": "None",
        "SubPath": ""
      },
      "LeaveParticle": {
        "Path": "None",
        "SubPath": ""
      },
      "bDisableOther": true,
      "ChangGround": false,
      "ShowEntryNotifyInfo": false,
      "ShowLeaveNotifyInfo": false,
      "IsQuestGroup": true,
      "KeepSkateboardState": false,
      "KeepAllState": false,
      "QuestList": []
    },
    "v602007": {
      "GroupId": -1,
      "GroupLevelId": "None",
      "LeaveDelayTime": 3,
      "Level": {
        "Path": "/Game/Resources/CoreBlueprints/SceneItem/vera_zdy/sidequest/v602005.v602005",
        "SubPath": ""
      },
      "EntryParticle": {
        "Path": "None",
        "SubPath": ""
      },
      "LeaveParticle": {
        "Path": "None",
        "SubPath": ""
      },
      "bDisableOther": true,
      "ChangGround": false,
      "ShowEntryNotifyInfo": false,
      "ShowLeaveNotifyInfo": false,
      "IsQuestGroup": true,
      "KeepSkateboardState": false,
      "KeepAllState": false,
      "QuestList": []
    },
    "v602010": {
      "GroupId": -1,
      "GroupLevelId": "None",
      "LeaveDelayTime": 3,
      "Level": {
        "Path": "/Game/Resources/CoreBlueprints/SceneItem/vera_zdy/sidequest/v602010.v602010",
        "SubPath": ""
      },
      "EntryParticle": {
        "Path": "None",
        "SubPath": ""
      },
      "LeaveParticle": {
        "Path": "None",
        "SubPath": ""
      },
      "bDisableOther": true,
      "ChangGround": false,
      "ShowEntryNotifyInfo": false,
      "ShowLeaveNotifyInfo": false,
      "IsQuestGroup": true,
      "KeepSkateboardState": false,
      "KeepAllState": false,
      "QuestList": []
    },
    "v602011": {
      "GroupId": -1,
      "GroupLevelId": "None",
      "LeaveDelayTime": 3,
      "Level": {
        "Path": "/Game/Resources/CoreBlueprints/SceneItem/vera_zdy/sidequest/v602010.v602010",
        "SubPath": ""
      },
      "EntryParticle": {
        "Path": "None",
        "SubPath": ""
      },
      "LeaveParticle": {
        "Path": "None",
        "SubPath": ""
      },
      "bDisableOther": true,
      "ChangGround": false,
      "ShowEntryNotifyInfo": false,
      "ShowLeaveNotifyInfo": false,
      "IsQuestGroup": true,
      "KeepSkateboardState": false,
      "KeepAllState": false,
      "QuestList": []
    },
    "v602012": {
      "GroupId": -1,
      "GroupLevelId": "None",
      "LeaveDelayTime": 3,
      "Level": {
        "Path": "/Game/Resources/CoreBlueprints/SceneItem/vera_zdy/sidequest/v602010.v602010",
        "SubPath": ""
      },
      "EntryParticle": {
        "Path": "None",
        "SubPath": ""
      },
      "LeaveParticle": {
        "Path": "None",
        "SubPath": ""
      },
      "bDisableOther": true,
      "ChangGround": false,
      "ShowEntryNotifyInfo": false,
      "ShowLeaveNotifyInfo": false,
      "IsQuestGroup": true,
      "KeepSkateboardState": false,
      "KeepAllState": false,
      "QuestList": []
    },
    "v602013": {
      "GroupId": -1,
      "GroupLevelId": "None",
      "LeaveDelayTime": 3,
      "Level": {
        "Path": "/Game/Resources/CoreBlueprints/SceneItem/vera_zdy/sidequest/v602010.v602010",
        "SubPath": ""
      },
      "EntryParticle": {
        "Path": "None",
        "SubPath": ""
      },
      "LeaveParticle": {
        "Path": "None",
        "SubPath": ""
      },
      "bDisableOther": true,
      "ChangGround": false,
      "ShowEntryNotifyInfo": false,
      "ShowLeaveNotifyInfo": false,
      "IsQuestGroup": true,
      "KeepSkateboardState": false,
      "KeepAllState": false,
      "QuestList": []
    },
    "v602014": {
      "GroupId": -1,
      "GroupLevelId": "None",
      "LeaveDelayTime": 3,
      "Level": {
        "Path": "/Game/Resources/CoreBlueprints/SceneItem/vera_zdy/sidequest/v602010.v602010",
        "SubPath": ""
      },
      "EntryParticle": {
        "Path": "None",
        "SubPath": ""
      },
      "LeaveParticle": {
        "Path": "None",
        "SubPath": ""
      },
      "bDisableOther": true,
      "ChangGround": false,
      "ShowEntryNotifyInfo": false,
      "ShowLeaveNotifyInfo": false,
      "IsQuestGroup": true,
      "KeepSkateboardState": false,
      "KeepAllState": false,
      "QuestList": []
    },
    "v602015": {
      "GroupId": -1,
      "GroupLevelId": "None",
      "LeaveDelayTime": 3,
      "Level": {
        "Path": "/Game/Resources/CoreBlueprints/SceneItem/vera_zdy/sidequest/v602010.v602010",
        "SubPath": ""
      },
      "EntryParticle": {
        "Path": "None",
        "SubPath": ""
      },
      "LeaveParticle": {
        "Path": "None",
        "SubPath": ""
      },
      "bDisableOther": true,
      "ChangGround": false,
      "ShowEntryNotifyInfo": false,
      "ShowLeaveNotifyInfo": false,
      "IsQuestGroup": true,
      "KeepSkateboardState": false,
      "KeepAllState": false,
      "QuestList": []
    },
    "v2010051": {
      "GroupId": -1,
      "GroupLevelId": "None",
      "LeaveDelayTime": 3,
      "Level": {
        "Path": "/Game/Resources/CoreBlueprints/SceneItem/vera_zdy/sidequest/v201005.v201005",
        "SubPath": ""
      },
      "EntryParticle": {
        "Path": "None",
        "SubPath": ""
      },
      "LeaveParticle": {
        "Path": "None",
        "SubPath": ""
      },
      "bDisableOther": true,
      "ChangGround": false,
      "ShowEntryNotifyInfo": false,
      "ShowLeaveNotifyInfo": false,
      "IsQuestGroup": true,
      "KeepSkateboardState": false,
      "KeepAllState": false,
      "QuestList": []
    },
    "v203004": {
      "GroupId": -1,
      "GroupLevelId": "None",
      "LeaveDelayTime": 3,
      "Level": {
        "Path": "/Game/Resources/CoreBlueprints/SceneItem/vera_zdy/sidequest/v203005.v203005",
        "SubPath": ""
      },
      "EntryParticle": {
        "Path": "None",
        "SubPath": ""
      },
      "LeaveParticle": {
        "Path": "None",
        "SubPath": ""
      },
      "bDisableOther": true,
      "ChangGround": false,
      "ShowEntryNotifyInfo": false,
      "ShowLeaveNotifyInfo": false,
      "IsQuestGroup": true,
      "KeepSkateboardState": false,
      "KeepAllState": false,
      "QuestList": []
    },
    "v203005": {
      "GroupId": -1,
      "GroupLevelId": "None",
      "LeaveDelayTime": 3,
      "Level": {
        "Path": "/Game/Resources/CoreBlueprints/SceneItem/vera_zdy/sidequest/v203005.v203005",
        "SubPath": ""
      },
      "EntryParticle": {
        "Path": "None",
        "SubPath": ""
      },
      "LeaveParticle": {
        "Path": "None",
        "SubPath": ""
      },
      "bDisableOther": true,
      "ChangGround": false,
      "ShowEntryNotifyInfo": false,
      "ShowLeaveNotifyInfo": false,
      "IsQuestGroup": true,
      "KeepSkateboardState": false,
      "KeepAllState": false,
      "QuestList": []
    },
    "v207002": {
      "GroupId": -1,
      "GroupLevelId": "None",
      "LeaveDelayTime": 3,
      "Level": {
        "Path": "/Game/Resources/CoreBlueprints/SceneItem/vera_zdy/sidequest/v207002.v207002",
        "SubPath": ""
      },
      "EntryParticle": {
        "Path": "None",
        "SubPath": ""
      },
      "LeaveParticle": {
        "Path": "None",
        "SubPath": ""
      },
      "bDisableOther": true,
      "ChangGround": false,
      "ShowEntryNotifyInfo": false,
      "ShowLeaveNotifyInfo": false,
      "IsQuestGroup": true,
      "KeepSkateboardState": false,
      "KeepAllState": false,
      "QuestList": []
    },
    "v207003": {
      "GroupId": -1,
      "GroupLevelId": "None",
      "LeaveDelayTime": 3,
      "Level": {
        "Path": "/Game/Resources/CoreBlueprints/SceneItem/vera_zdy/sidequest/v207002.v207002",
        "SubPath": ""
      },
      "EntryParticle": {
        "Path": "None",
        "SubPath": ""
      },
      "LeaveParticle": {
        "Path": "None",
        "SubPath": ""
      },
      "bDisableOther": true,
      "ChangGround": false,
      "ShowEntryNotifyInfo": false,
      "ShowLeaveNotifyInfo": false,
      "IsQuestGroup": true,
      "KeepSkateboardState": false,
      "KeepAllState": false,
      "QuestList": []
    },
    "v208002": {
      "GroupId": -1,
      "GroupLevelId": "None",
      "LeaveDelayTime": 3,
      "Level": {
        "Path": "/Game/Resources/CoreBlueprints/SceneItem/vera_zdy/sidequest/v208002.v208002",
        "SubPath": ""
      },
      "EntryParticle": {
        "Path": "None",
        "SubPath": ""
      },
      "LeaveParticle": {
        "Path": "None",
        "SubPath": ""
      },
      "bDisableOther": true,
      "ChangGround": false,
      "ShowEntryNotifyInfo": false,
      "ShowLeaveNotifyInfo": false,
      "IsQuestGroup": true,
      "KeepSkateboardState": false,
      "KeepAllState": false,
      "QuestList": []
    },
    "v208003": {
      "GroupId": -1,
      "GroupLevelId": "None",
      "LeaveDelayTime": 3,
      "Level": {
        "Path": "/Game/Resources/CoreBlueprints/SceneItem/vera_zdy/sidequest/v208002.v208002",
        "SubPath": ""
      },
      "EntryParticle": {
        "Path": "None",
        "SubPath": ""
      },
      "LeaveParticle": {
        "Path": "None",
        "SubPath": ""
      },
      "bDisableOther": true,
      "ChangGround": false,
      "ShowEntryNotifyInfo": false,
      "ShowLeaveNotifyInfo": false,
      "IsQuestGroup": true,
      "KeepSkateboardState": false,
      "KeepAllState": false,
      "QuestList": []
    },
    "v212007": {
      "GroupId": -1,
      "GroupLevelId": "None",
      "LeaveDelayTime": 3,
      "Level": {
        "Path": "/Game/Resources/CoreBlueprints/SceneItem/vera_zdy/sidequest/v212008.v212008",
        "SubPath": ""
      },
      "EntryParticle": {
        "Path": "None",
        "SubPath": ""
      },
      "LeaveParticle": {
        "Path": "None",
        "SubPath": ""
      },
      "bDisableOther": true,
      "ChangGround": false,
      "ShowEntryNotifyInfo": false,
      "ShowLeaveNotifyInfo": false,
      "IsQuestGroup": true,
      "KeepSkateboardState": false,
      "KeepAllState": false,
      "QuestList": []
    },
    "v218015": {
      "GroupId": -1,
      "GroupLevelId": "None",
      "LeaveDelayTime": 3,
      "Level": {
        "Path": "/Game/Resources/CoreBlueprints/SceneItem/vera_zdy/sidequest/v218018.v218018",
        "SubPath": ""
      },
      "EntryParticle": {
        "Path": "None",
        "SubPath": ""
      },
      "LeaveParticle": {
        "Path": "None",
        "SubPath": ""
      },
      "bDisableOther": true,
      "ChangGround": false,
      "ShowEntryNotifyInfo": false,
      "ShowLeaveNotifyInfo": false,
      "IsQuestGroup": true,
      "KeepSkateboardState": false,
      "KeepAllState": false,
      "QuestList": []
    },
    "v218016": {
      "GroupId": -1,
      "GroupLevelId": "None",
      "LeaveDelayTime": 3,
      "Level": {
        "Path": "/Game/Resources/CoreBlueprints/SceneItem/vera_zdy/sidequest/v218018.v218018",
        "SubPath": ""
      },
      "EntryParticle": {
        "Path": "None",
        "SubPath": ""
      },
      "LeaveParticle": {
        "Path": "None",
        "SubPath": ""
      },
      "bDisableOther": true,
      "ChangGround": false,
      "ShowEntryNotifyInfo": false,
      "ShowLeaveNotifyInfo": false,
      "IsQuestGroup": true,
      "KeepSkateboardState": false,
      "KeepAllState": false,
      "QuestList": []
    },
    "v218017": {
      "GroupId": -1,
      "GroupLevelId": "None",
      "LeaveDelayTime": 3,
      "Level": {
        "Path": "/Game/Resources/CoreBlueprints/SceneItem/vera_zdy/sidequest/v218018.v218018",
        "SubPath": ""
      },
      "EntryParticle": {
        "Path": "None",
        "SubPath": ""
      },
      "LeaveParticle": {
        "Path": "None",
        "SubPath": ""
      },
      "bDisableOther": true,
      "ChangGround": false,
      "ShowEntryNotifyInfo": false,
      "ShowLeaveNotifyInfo": false,
      "IsQuestGroup": true,
      "KeepSkateboardState": false,
      "KeepAllState": false,
      "QuestList": []
    },
    "v219006": {
      "GroupId": -1,
      "GroupLevelId": "None",
      "LeaveDelayTime": 3,
      "Level": {
        "Path": "/Game/Resources/CoreBlueprints/SceneItem/vera_zdy/sidequest/CarryBox_sidequest_v21900.CarryBox_sidequest_v21900",
        "SubPath": ""
      },
      "EntryParticle": {
        "Path": "None",
        "SubPath": ""
      },
      "LeaveParticle": {
        "Path": "None",
        "SubPath": ""
      },
      "bDisableOther": true,
      "ChangGround": false,
      "ShowEntryNotifyInfo": false,
      "ShowLeaveNotifyInfo": false,
      "IsQuestGroup": true,
      "KeepSkateboardState": false,
      "KeepAllState": false,
      "QuestList": []
    },
    "Vera_Taxi_A4": {
      "GroupId": -1,
      "GroupLevelId": "None",
      "LeaveDelayTime": 0,
      "Level": {
        "Path": "/Game/Resources/CoreBlueprints/Trial/Vera_city/Taxi/Vera_Taxi_A4.Vera_Taxi_A4",
        "SubPath": ""
      },
      "EntryParticle": {
        "Path": "None",
        "SubPath": ""
      },
      "LeaveParticle": {
        "Path": "None",
        "SubPath": ""
      },
      "bDisableOther": true,
      "ChangGround": true,
      "ShowEntryNotifyInfo": false,
      "ShowLeaveNotifyInfo": false,
      "IsQuestGroup": false,
      "KeepSkateboardState": false,
      "KeepAllState": false,
      "QuestList": []
    },
    "Vera_Taxi_Centre": {
      "GroupId": -1,
      "GroupLevelId": "None",
      "LeaveDelayTime": 0,
      "Level": {
        "Path": "/Game/Resources/CoreBlueprints/Trial/Vera_city/Taxi/Vera_Taxi_Centre.Vera_Taxi_Centre",
        "SubPath": ""
      },
      "EntryParticle": {
        "Path": "None",
        "SubPath": ""
      },
      "LeaveParticle": {
        "Path": "None",
        "SubPath": ""
      },
      "bDisableOther": true,
      "ChangGround": true,
      "ShowEntryNotifyInfo": false,
      "ShowLeaveNotifyInfo": false,
      "IsQuestGroup": false,
      "KeepSkateboardState": false,
      "KeepAllState": false,
      "QuestList": []
    },
    "Vera_Taxi_JieDai": {
      "GroupId": -1,
      "GroupLevelId": "None",
      "LeaveDelayTime": 0,
      "Level": {
        "Path": "/Game/Resources/CoreBlueprints/Trial/Vera_city/Taxi/Vera_Taxi_JieDai.Vera_Taxi_JieDai",
        "SubPath": ""
      },
      "EntryParticle": {
        "Path": "None",
        "SubPath": ""
      },
      "LeaveParticle": {
        "Path": "None",
        "SubPath": ""
      },
      "bDisableOther": true,
      "ChangGround": true,
      "ShowEntryNotifyInfo": false,
      "ShowLeaveNotifyInfo": false,
      "IsQuestGroup": false,
      "KeepSkateboardState": false,
      "KeepAllState": false,
      "QuestList": []
    },
    "Vera_Taxi_B4": {
      "GroupId": -1,
      "GroupLevelId": "None",
      "LeaveDelayTime": 0,
      "Level": {
        "Path": "/Game/Resources/CoreBlueprints/Trial/Vera_city/Taxi/Vera_Taxi_B4.Vera_Taxi_B4",
        "SubPath": ""
      },
      "EntryParticle": {
        "Path": "None",
        "SubPath": ""
      },
      "LeaveParticle": {
        "Path": "None",
        "SubPath": ""
      },
      "bDisableOther": true,
      "ChangGround": true,
      "ShowEntryNotifyInfo": false,
      "ShowLeaveNotifyInfo": false,
      "IsQuestGroup": false,
      "KeepSkateboardState": false,
      "KeepAllState": false,
      "QuestList": []
    },
    "RollBall": {
      "GroupId": -1,
      "GroupLevelId": "None",
      "LeaveDelayTime": 3,
      "Level": {
        "Path": "/Game/Resources/DynamicLevels/MiniGame/Vera_City/RollBall/RollBall.RollBall",
        "SubPath": ""
      },
      "EntryParticle": {
        "Path": "None",
        "SubPath": ""
      },
      "LeaveParticle": {
        "Path": "None",
        "SubPath": ""
      },
      "bDisableOther": true,
      "ChangGround": true,
      "ShowEntryNotifyInfo": false,
      "ShowLeaveNotifyInfo": false,
      "IsQuestGroup": false,
      "KeepSkateboardState": false,
      "KeepAllState": false,
      "QuestList": []
    },
    "LaserJump": {
      "GroupId": -1,
      "GroupLevelId": "None",
      "LeaveDelayTime": 3,
      "Level": {
        "Path": "/Game/Resources/DynamicLevels/MiniGame/Vera_City/LaserJump/LaserJump.LaserJump",
        "SubPath": ""
      },
      "EntryParticle": {
        "Path": "None",
        "SubPath": ""
      },
      "LeaveParticle": {
        "Path": "None",
        "SubPath": ""
      },
      "bDisableOther": true,
      "ChangGround": true,
      "ShowEntryNotifyInfo": false,
      "ShowLeaveNotifyInfo": false,
      "IsQuestGroup": false,
      "KeepSkateboardState": false,
      "KeepAllState": false,
      "QuestList": []
    },
    "Vera_plane_huiyu": {
      "GroupId": -1,
      "GroupLevelId": "None",
      "LeaveDelayTime": 1,
      "Level": {
        "Path": "/Game/Resources/DynamicLevels/Vera_plane_huiyu.Vera_plane_huiyu",
        "SubPath": ""
      },
      "EntryParticle": {
        "Path": "None",
        "SubPath": ""
      },
      "LeaveParticle": {
        "Path": "None",
        "SubPath": ""
      },
      "bDisableOther": true,
      "ChangGround": true,
      "ShowEntryNotifyInfo": false,
      "ShowLeaveNotifyInfo": false,
      "IsQuestGroup": false,
      "KeepSkateboardState": false,
      "KeepAllState": false,
      "QuestList": []
    },
    "MoveArchery": {
      "GroupId": -1,
      "GroupLevelId": "None",
      "LeaveDelayTime": 3,
      "Level": {
        "Path": "/Game/Resources/DynamicLevels/MiniGame/Vera_City/MoveArchery/MoveArchery.MoveArchery",
        "SubPath": ""
      },
      "EntryParticle": {
        "Path": "None",
        "SubPath": ""
      },
      "LeaveParticle": {
        "Path": "None",
        "SubPath": ""
      },
      "bDisableOther": true,
      "ChangGround": true,
      "ShowEntryNotifyInfo": false,
      "ShowLeaveNotifyInfo": false,
      "IsQuestGroup": false,
      "KeepSkateboardState": false,
      "KeepAllState": false,
      "QuestList": []
    },
    "MoveShoot": {
      "GroupId": -1,
      "GroupLevelId": "None",
      "LeaveDelayTime": 3,
      "Level": {
        "Path": "/Game/Resources/DynamicLevels/MiniGame/Vera_City/MoveShoot/MoveShoot.MoveShoot",
        "SubPath": ""
      },
      "EntryParticle": {
        "Path": "None",
        "SubPath": ""
      },
      "LeaveParticle": {
        "Path": "None",
        "SubPath": ""
      },
      "bDisableOther": true,
      "ChangGround": true,
      "ShowEntryNotifyInfo": false,
      "ShowLeaveNotifyInfo": false,
      "IsQuestGroup": false,
      "KeepSkateboardState": false,
      "KeepAllState": false,
      "QuestList": []
    },
    "NoteACrash_VeraCity": {
      "GroupId": -1,
      "GroupLevelId": "None",
      "LeaveDelayTime": 3,
      "Level": {
        "Path": "/Game/Resources/DynamicLevels/MiniGame/Vera_City/NoteACrash/NoteACrash_VeraCity.NoteACrash_VeraCity",
        "SubPath": ""
      },
      "EntryParticle": {
        "Path": "None",
        "SubPath": ""
      },
      "LeaveParticle": {
        "Path": "None",
        "SubPath": ""
      },
      "bDisableOther": true,
      "ChangGround": true,
      "ShowEntryNotifyInfo": false,
      "ShowLeaveNotifyInfo": false,
      "IsQuestGroup": false,
      "KeepSkateboardState": false,
      "KeepAllState": false,
      "QuestList": []
    },
    "CarryBox": {
      "GroupId": -1,
      "GroupLevelId": "None",
      "LeaveDelayTime": 3,
      "Level": {
        "Path": "/Game/Resources/DynamicLevels/MiniGame/Vera_City/CarryBox/CarryBox.CarryBox",
        "SubPath": ""
      },
      "EntryParticle": {
        "Path": "None",
        "SubPath": ""
      },
      "LeaveParticle": {
        "Path": "None",
        "SubPath": ""
      },
      "bDisableOther": true,
      "ChangGround": true,
      "ShowEntryNotifyInfo": false,
      "ShowLeaveNotifyInfo": false,
      "IsQuestGroup": false,
      "KeepSkateboardState": false,
      "KeepAllState": false,
      "QuestList": []
    },
    "Cinematic": {
      "GroupId": -1,
      "GroupLevelId": "None",
      "LeaveDelayTime": 0,
      "Level": {
        "Path": "None",
        "SubPath": ""
      },
      "EntryParticle": {
        "Path": "None",
        "SubPath": ""
      },
      "LeaveParticle": {
        "Path": "None",
        "SubPath": ""
      },
      "bDisableOther": false,
      "ChangGround": false,
      "ShowEntryNotifyInfo": false,
      "ShowLeaveNotifyInfo": false,
      "IsQuestGroup": false,
      "KeepSkateboardState": false,
      "KeepAllState": true,
      "QuestList": []
    },
    "cooking": {
      "GroupId": -1,
      "GroupLevelId": "None",
      "LeaveDelayTime": 1,
      "Level": {
        "Path": "/Game/Resources/DynamicLevels/cooking.cooking",
        "SubPath": ""
      },
      "EntryParticle": {
        "Path": "None",
        "SubPath": ""
      },
      "LeaveParticle": {
        "Path": "None",
        "SubPath": ""
      },
      "bDisableOther": false,
      "ChangGround": false,
      "ShowEntryNotifyInfo": false,
      "ShowLeaveNotifyInfo": false,
      "IsQuestGroup": false,
      "KeepSkateboardState": false,
      "KeepAllState": false,
      "QuestList": []
    }
  }
  }
]